wst/__init__.py
wst/conf.py
wst/shell.py
wst/version.py
wst/builder/__init__.py
wst/builder/cmake.py
wst/builder/meson.py
wst/builder/setuptools.py
wst/cmd/__init__.py
wst/cmd/build.py
wst/cmd/clean.py
wst/cmd/config.py
wst/cmd/default.py
wst/cmd/env.py
wst/cmd/init.py
wst/cmd/list.py
wst/cmd/remove.py
wst/cmd/rename.py
wst/cmd/test.py
wst-1.0.18.data/data/share/bash-completion/completions/ws
wst-1.0.18.data/scripts/ws
wst-1.0.18.dist-info/LICENSE
wst-1.0.18.dist-info/METADATA
wst-1.0.18.dist-info/WHEEL
wst-1.0.18.dist-info/top_level.txt
wst-1.0.18.dist-info/RECORD
