Metadata-Version: 2.1
Name: wst
Version: 1.0.18
Summary: A lightweight tool for managing a workspace of repositories
Home-page: UNKNOWN
Author: Martin Kelly
Author-email: mkelly@xevo.com
License: BSD
Platform: UNKNOWN
Classifier: Development Status :: 3 - Alpha
Classifier: Environment :: Console
Classifier: Intended Audience :: Developers
Classifier: License :: OSI Approved :: BSD License
Classifier: Natural Language :: English
Classifier: Operating System :: POSIX :: Linux
Classifier: Programming Language :: Python :: 3 :: Only
Classifier: Topic :: Software Development :: Build Tools
Requires-Python: >=3
Requires-Dist: PyYAML
